tradesignals/__init__.py
tradesignals/_base_client.py
tradesignals/_client.py
tradesignals/_compat.py
tradesignals/_constants.py
tradesignals/_exceptions.py
tradesignals/_files.py
tradesignals/_models.py
tradesignals/_qs.py
tradesignals/_resource.py
tradesignals/_response.py
tradesignals/_streaming.py
tradesignals/_types.py
tradesignals/_version.py
tradesignals/_wrappers.py
tradesignals/py.typed
tradesignals/_utils/__init__.py
tradesignals/_utils/_logs.py
tradesignals/_utils/_proxy.py
tradesignals/_utils/_reflection.py
tradesignals/_utils/_streams.py
tradesignals/_utils/_sync.py
tradesignals/_utils/_transform.py
tradesignals/_utils/_typing.py
tradesignals/_utils/_utils.py
tradesignals/lib/.keep
tradesignals/resources/__init__.py
tradesignals/resources/analyst/__init__.py
tradesignals/resources/analyst/analyst.py
tradesignals/resources/analyst/ratings.py
tradesignals/resources/congress/__init__.py
tradesignals/resources/congress/congress.py
tradesignals/resources/congress/congress_member_trades.py
tradesignals/resources/congress/recent_reports.py
tradesignals/resources/congress/trades_by_member.py
tradesignals/resources/congress/trades_reported_late.py
tradesignals/resources/darkpool/__init__.py
tradesignals/resources/darkpool/darkpool.py
tradesignals/resources/darkpool/recent_trades.py
tradesignals/resources/darkpool/trades_by_ticker.py
tradesignals/resources/earnings/__init__.py
tradesignals/resources/earnings/afterhours_earnings.py
tradesignals/resources/earnings/earnings.py
tradesignals/resources/earnings/historical_earnings.py
tradesignals/resources/earnings/premarket_earnings.py
tradesignals/resources/etf/__init__.py
tradesignals/resources/etf/etf.py
tradesignals/resources/etf/exposure.py
tradesignals/resources/etf/holdings.py
tradesignals/resources/etf/inflows_outflows.py
tradesignals/resources/etf/information.py
tradesignals/resources/etf/weights.py
tradesignals/resources/industry/__init__.py
tradesignals/resources/industry/greek_flow.py
tradesignals_python-0.1.0a10.dist-info/METADATA
tradesignals_python-0.1.0a10.dist-info/WHEEL
tradesignals_python-0.1.0a10.dist-info/licenses/LICENSE.md
tradesignals_python-0.1.0a10.dist-info/RECORD
